datapath.v
module datapath(
    input clk,rst,load,add_en,sub_en,shift_en,
    input [3:0] M_in,Q_in,
    output reg [7:0] res,
    output q0,qn1
);

reg [3:0] acc,Q,M;
reg Qn1;

assign q0=Q[0];
assign qn1=Qn1;

always@(posedge clk or posedge rst)begin
    if(rst)begin
        res<=8'b0;
        Qn1<=0;
        acc<=4'b0;
        Q<=4'b0;
        M<=4'b0;
    end
    else if(load)begin
        M<=M_in;
        Q<=Q_in;
        acc<=0;
        Qn1<=0;
    end
    else if(shift_en)begin
        {acc,Q,Qn1} <= {acc[3],acc,Q};
    end
    else if(add_en)begin
        acc <= acc+M;
    end
    else if(sub_en)begin
        acc <= acc-M;
    end
    res<={acc,Q};
end


endmodule

controller.v
module controller(
    input clk,start,rst,
    input [3:0] q,m,
    input q0, qn1,
    output reg add_en,shift_en,sub_en,load,
    output reg [3:0] Q_in,M_in,
    output reg done
);

localparam [2:0] IDLE = 3'b000,
LOAD = 3'b001,
CHECK = 3'b010,
ADD = 3'b011,
SUB = 3'b100,
SHIFT = 3'b101,
DONE = 3'b110;

reg [2:0] curr_state,next_state;
reg [2:0] count;

always@(posedge clk or posedge rst)begin
    if(rst)begin
        curr_state<=IDLE;
        count<=3'd0;
    end
    else begin
        curr_state<=next_state;
        if(curr_state == SHIFT)count<=count+1;
        else if(curr_state == LOAD)count<=3'd0;
    end
end

always@(*)begin
    next_state = curr_state;
    case(curr_state)
    IDLE : begin
        if(start)next_state = LOAD;
    end
    LOAD : next_state = CHECK;
    CHECK : begin
        if(count == 3'd4)begin
            next_state=DONE;
        end
        else begin
            case({q0,qn1})
            2'b00 : next_state = SHIFT;
            2'b11 : next_state = SHIFT;
            2'b10 : next_state = SUB;
            2'b01 : next_state = ADD;
            endcase
        end
    end
    ADD : next_state = SHIFT;
    SUB : next_state = SHIFT;
    SHIFT : next_state = CHECK;
    DONE : next_state = IDLE;
    default : next_state = IDLE;
    endcase
end

always@(*)begin
    load=0;
    add_en=0;
    sub_en=0;
    shift_en=0;
    done=0;
    Q_in=4'b0;
    M_in=4'b0;

    case(curr_state)
    IDLE : load = 0;
    LOAD : begin
        load = 1;
        Q_in=q;
        M_in=m;
    end
    ADD : add_en = 1;
    SUB : sub_en = 1;
    SHIFT : shift_en = 1;
    DONE : done=1;
    default : load =0;
    endcase
end
endmodule

topmodule.v
module topmodule(
    input clk,rst,start,
    input [3:0] Q,M,
    output [7:0] result,
    output done_top
);

wire load,add_en,sub_en,shift_en,q0,qn1,done;
wire [3:0] M_in,Q_in;

assign done_top = done;

controller ctrl(
    .clk(clk), .start(start), .rst(rst),
    .q(Q), .m(M), .q0(q0), .qn1(qn1),
    .add_en(add_en), .shift_en(shift_en), .sub_en(sub_en), .load(load),
    .Q_in(Q_in), .M_in(M_in), .done(done) 
);

datapath dp(
    .clk(clk), .rst(rst), .load(load),
    .add_en(add_en), .sub_en(sub_en), .shift_en(shift_en),
    .M_in(M_in), .Q_in(Q_in), .res(result), .q0(q0), .qn1(qn1)
);


endmodule

tb.v
module tb;

wire [7:0] result;
wire done;
reg clk,rst,start;
reg [3:0] Q,M;

topmodule DUT(.clk(clk), .rst(rst), .start(start), .Q(Q), .M(M)
,.result(result), .done_top(done));

initial clk=0;
always #10 clk=~clk;

initial begin
    $dumpfile("wave.vcd");
    $dumpvars(0,tb);
    $monitor("Rst=%b  |  Start=%b  |  Q=%b  |  M=%b  | Done=%b  | Result=%b",rst,start,Q,M,done,result);
    rst=1;start=0;
    #20 rst=0;Q=4'b0011;M=4'b1010;
    #20 start=1;
    #20 start=0;
    #500
    $display("\nFinal Result: %b (decimal: %d)", result, result);
    $display("Expected: 3 × 3 = 9 = 00001001");
    $finish; 
    $finish;
end

endmodule

wave.vcd
$date
	Sun Nov 16 12:24:16 2025
$end
$version
	Icarus Verilog
$end
$timescale
	1s
$end
$scope module tb $end
$var wire 8 ! result [7:0] $end
$var wire 1 " done $end
$var reg 4 # M [3:0] $end
$var reg 4 $ Q [3:0] $end
$var reg 1 % clk $end
$var reg 1 & rst $end
$var reg 1 ' start $end
$scope module DUT $end
$var wire 4 ( M [3:0] $end
$var wire 4 ) Q [3:0] $end
$var wire 1 % clk $end
$var wire 1 " done_top $end
$var wire 1 & rst $end
$var wire 1 ' start $end
$var wire 1 * sub_en $end
$var wire 1 + shift_en $end
$var wire 8 , result [7:0] $end
$var wire 1 - qn1 $end
$var wire 1 . q0 $end
$var wire 1 / load $end
$var wire 1 0 done $end
$var wire 1 1 add_en $end
$var wire 4 2 Q_in [3:0] $end
$var wire 4 3 M_in [3:0] $end
$scope module ctrl $end
$var wire 1 % clk $end
$var wire 4 4 m [3:0] $end
$var wire 4 5 q [3:0] $end
$var wire 1 & rst $end
$var wire 1 ' start $end
$var wire 1 - qn1 $end
$var wire 1 . q0 $end
$var parameter 3 6 ADD $end
$var parameter 3 7 CHECK $end
$var parameter 3 8 DONE $end
$var parameter 3 9 IDLE $end
$var parameter 3 : LOAD $end
$var parameter 3 ; SHIFT $end
$var parameter 3 < SUB $end
$var reg 4 = M_in [3:0] $end
$var reg 4 > Q_in [3:0] $end
$var reg 1 1 add_en $end
$var reg 3 ? count [2:0] $end
$var reg 3 @ curr_state [2:0] $end
$var reg 1 0 done $end
$var reg 1 / load $end
$var reg 3 A next_state [2:0] $end
$var reg 1 + shift_en $end
$var reg 1 * sub_en $end
$upscope $end
$scope module dp $end
$var wire 4 B M_in [3:0] $end
$var wire 4 C Q_in [3:0] $end
$var wire 1 1 add_en $end
$var wire 1 % clk $end
$var wire 1 / load $end
$var wire 1 - qn1 $end
$var wire 1 & rst $end
$var wire 1 + shift_en $end
$var wire 1 * sub_en $end
$var wire 1 . q0 $end
$var reg 4 D M [3:0] $end
$var reg 4 E Q [3:0] $end
$var reg 1 F Qn1 $end
$var reg 4 G acc [3:0] $end
$var reg 8 H res [7:0] $end
$upscope $end
$upscope $end
$upscope $end
$enddefinitions $end
$comment Show the parameter values. $end
$dumpall
b100 <
b101 ;
b1 :
b0 9
b110 8
b10 7
b11 6
$end
#0
$dumpvars
bx H
b0 G
0F
b0 E
b0 D
b0 C
b0 B
b0 A
b0 @
b0 ?
b0 >
b0 =
bx 5
bx 4
b0 3
b0 2
01
00
0/
0.
0-
bx ,
0+
0*
bx )
bx (
0'
1&
0%
bx $
bx #
0"
bx !
$end
#10
b0 !
b0 ,
b0 H
1%
#20
0%
b1010 #
b1010 (
b1010 4
b11 $
b11 )
b11 5
0&
#30
1%
#40
b1 A
0%
1'
#50
b1010 3
b1010 =
b1010 B
b11 2
b11 >
b11 C
1/
b10 A
b1 @
1%
#60
b10 A
0%
0'
#70
b0 3
b0 =
b0 B
b0 2
b0 >
b0 C
0/
b100 A
1.
b10 @
b11 E
b1010 D
1%
#80
0%
#90
1*
b101 A
b11 !
b11 ,
b11 H
b100 @
1%
#100
0%
#110
1+
0*
b10 A
b101 @
b110 G
1%
#120
0%
#130
0+
b101 A
b1100011 !
b1100011 ,
b1100011 H
b11 G
b1 E
1-
1F
b1 ?
b10 @
1%
#140
0%
#150
1+
b10 A
b101 @
b110001 !
b110001 ,
b110001 H
1%
#160
0%
#170
0.
0+
b11 A
b1 G
b1000 E
b10 ?
b10 @
1%
#180
0%
#190
11
b101 A
b11 @
b11000 !
b11000 ,
b11000 H
1%
#200
0%
#210
1+
01
b10 A
b1011 G
b101 @
1%
#220
0%
#230
0+
b101 A
b11 ?
b10 @
b10111000 !
b10111000 ,
b10111000 H
b1101 G
b1100 E
0-
0F
1%
#240
0%
#250
1+
b10 A
b11011100 !
b11011100 ,
b11011100 H
b101 @
1%
#260
0%
#270
0+
b110 A
b100 ?
b10 @
b1110 G
b1110 E
1%
#280
0%
#290
1"
10
b0 A
b11101110 !
b11101110 ,
b11101110 H
b110 @
1%
#300
0%
#310
0"
00
b0 @
1%
